{
  "tutorial": {
    "title": "FloidPro MakeCode Tutorial",
    "steps": [
      {
        "title": "Einleitung zum FloidPro",
        "description": "Willkommen zum FloidPro-Tutorial! Hier lernst du die Grundlagen der Hardware und Programmierung mit MakeCode."
      },
      {
        "title": "Überblick über die FloidPro-Hardware",
        "description": "Der FloidPro besteht aus verschiedenen Sensoren, LEDs und Motoren, die du einfach programmieren kannst."
      },
      {
        "title": "Programmieren mit MakeCode",
        "description": "In diesem Abschnitt zeigen wir, wie du Blöcke in MakeCode verbindest, um deinen FloidPro zum Leben zu erwecken.",
        "blocks": "<xml xmlns=\"https://developers.google.com/blockly/xml\"><block type=\"basic_showicon\" x=\"10\" y=\"10\"><field name=\"NAME\">Heart</field></block></xml>"
      },
      {
        "title": "Beispielprojekt: LED-Lichtspiel",
        "description": "Als Beispiel bauen wir ein einfaches LED-Lichtspiel. Hier zeigen wir dir Schritt für Schritt den Code.",
        "code": "basic.showLeds(`\n  # # # # #\n  # . . . #\n  # . # . #\n  # . . . #\n  # # # # #\n`)\nbasic.pause(500)\nbasic.clearScreen()"
      }
    ]
  }
}
